pychatapp/__init__.py
pychatapp/mainApp.py
pychatapp/main/mainApp.py
pychatapp-1.6.dist-info/LICENSE.txt
pychatapp-1.6.dist-info/METADATA
pychatapp-1.6.dist-info/WHEEL
pychatapp-1.6.dist-info/top_level.txt
pychatapp-1.6.dist-info/RECORD
