Metadata-Version: 2.1
Name: pychatapp
Version: 1.6
Summary: It is a chatting application written in Python, purpose of PyChatApp is to bring python community together and connect with various Pythonistas around the world.
Home-page: https://github.com/Ankit404butfound/pychatapp
Author: Ankit Raj Mahapatra
Author-email: ankitrajjitendra816@gmail.com
License: MIT
Keywords: start
Platform: UNKNOWN
Classifier: Development Status :: 3 - Alpha
Classifier: Intended Audience :: Developers
Classifier: Topic :: Software Development :: Build Tools
Classifier: License :: OSI Approved :: MIT License
Classifier: Programming Language :: Python :: 3
Classifier: Programming Language :: Python :: 3.4
Classifier: Programming Language :: Python :: 3.5
Classifier: Programming Language :: Python :: 3.6
Requires-Dist: plyer
Requires-Dist: requests
